ObjectiveCJichujiaocheng1TianWanzhuanObjectiveCYufa/README.md
ObjectiveCJichujiaocheng1TianWanzhuanObjectiveCYufa/__init__.py
ObjectiveCJichujiaocheng1TianWanzhuanObjectiveCYufa/__main__.py
ObjectiveCJichujiaocheng1TianWanzhuanObjectiveCYufa/file.epub
ObjectiveCJichujiaocheng1TianWanzhuanObjectiveCYufa/index.html
ObjectiveCJichujiaocheng1TianWanzhuanObjectiveCYufa/css/__init__.py
ObjectiveCJichujiaocheng1TianWanzhuanObjectiveCYufa/css/annotations.css
ObjectiveCJichujiaocheng1TianWanzhuanObjectiveCYufa/css/main.css
ObjectiveCJichujiaocheng1TianWanzhuanObjectiveCYufa/css/normalize.css
ObjectiveCJichujiaocheng1TianWanzhuanObjectiveCYufa/css/popup.css
ObjectiveCJichujiaocheng1TianWanzhuanObjectiveCYufa/font/__init__.py
ObjectiveCJichujiaocheng1TianWanzhuanObjectiveCYufa/font/fontello.eot
ObjectiveCJichujiaocheng1TianWanzhuanObjectiveCYufa/font/fontello.svg
ObjectiveCJichujiaocheng1TianWanzhuanObjectiveCYufa/font/fontello.ttf
ObjectiveCJichujiaocheng1TianWanzhuanObjectiveCYufa/font/fontello.woff
ObjectiveCJichujiaocheng1TianWanzhuanObjectiveCYufa/img/__init__.py
ObjectiveCJichujiaocheng1TianWanzhuanObjectiveCYufa/img/annotator-glyph-sprite.png
ObjectiveCJichujiaocheng1TianWanzhuanObjectiveCYufa/img/annotator-icon-sprite.png
ObjectiveCJichujiaocheng1TianWanzhuanObjectiveCYufa/img/apple-touch-icon.png
ObjectiveCJichujiaocheng1TianWanzhuanObjectiveCYufa/img/cancelfullscreen.png
ObjectiveCJichujiaocheng1TianWanzhuanObjectiveCYufa/img/close.png
ObjectiveCJichujiaocheng1TianWanzhuanObjectiveCYufa/img/fullscreen.png
ObjectiveCJichujiaocheng1TianWanzhuanObjectiveCYufa/img/loader.gif
ObjectiveCJichujiaocheng1TianWanzhuanObjectiveCYufa/img/menu-icon.png
ObjectiveCJichujiaocheng1TianWanzhuanObjectiveCYufa/img/save.png
ObjectiveCJichujiaocheng1TianWanzhuanObjectiveCYufa/img/saved.png
ObjectiveCJichujiaocheng1TianWanzhuanObjectiveCYufa/img/settings-s.png
ObjectiveCJichujiaocheng1TianWanzhuanObjectiveCYufa/img/settings.png
objective_c_jichujiaocheng_1_tian_wanzhuan_objective_c_yufa-2024.3.2.0.dist-info/METADATA
objective_c_jichujiaocheng_1_tian_wanzhuan_objective_c_yufa-2024.3.2.0.dist-info/WHEEL
objective_c_jichujiaocheng_1_tian_wanzhuan_objective_c_yufa-2024.3.2.0.dist-info/entry_points.txt
objective_c_jichujiaocheng_1_tian_wanzhuan_objective_c_yufa-2024.3.2.0.dist-info/top_level.txt
objective_c_jichujiaocheng_1_tian_wanzhuan_objective_c_yufa-2024.3.2.0.dist-info/RECORD
